clifold/__init__.py
clifold/clifold_main.py
clifold/commands/__init__.py
clifold/commands/clifold_git.py
clifold/commands/clifold_init.py
clifold/commands/clifold_pkg.py
clifold/commands/clifold_project.py
tests/__init__.py
tests/test_commands.py
tests/test_main.py
clifold-0.2.10.dist-info/LICENSE
clifold-0.2.10.dist-info/METADATA
clifold-0.2.10.dist-info/WHEEL
clifold-0.2.10.dist-info/entry_points.txt
clifold-0.2.10.dist-info/top_level.txt
clifold-0.2.10.dist-info/RECORD
