Metadata-Version: 2.1
Name: clifold
Version: 0.2.10
Summary: 🚀 A CLI tool for scaffolding any Python Projects 🚀
Home-page: https://github.com/ydcjeff/clifold
Author: Jeff Yang
Author-email: ydc.jeff@gmail.com
License: MIT
Keywords: scaffold python project cli
Platform: UNKNOWN
Classifier: Development Status :: 5 - Production/Stable
Classifier: Environment :: Console
Classifier: Intended Audience :: Developers
Classifier: Intended Audience :: Science/Research
Classifier: License :: OSI Approved :: MIT License
Classifier: Operating System :: OS Independent
Classifier: Programming Language :: Python :: 3.6
Classifier: Programming Language :: Python :: 3.7
Classifier: Programming Language :: Python :: 3.8
Classifier: Topic :: Utilities
Requires-Python: >=3.6.0
Requires-Dist: requests
Provides-Extra: test
Requires-Dist: pytest ; extra == 'test'
Requires-Dist: flake8 ; extra == 'test'
